Workbook
Name payload_kg: 'Параметры'!$C$3
Name swath_eff_m: 'Параметры'!$C$4
Name speed_ms: 'Параметры'!$C$5
Name overhead_min: 'Параметры'!$C$6
Name reload_min: 'Параметры'!$C$7
Name eff_hours_per_day: 'Параметры'!$C$8
Name days_per_season: 'Параметры'!$C$9
Name flow_kg_min: 'Параметры'!$C$10
Name cycle_equiv_min: 'Параметры'!$C$11
Name max_flight_min: 'Параметры'!$C$12
Name battery_price_usd: 'Параметры'!$C$14
Name battery_cycles: 'Параметры'!$C$15
Name battery_kwh: 'Параметры'!$C$16
Name gen_l_per_kwh: 'Параметры'!$C$17
Name charge_eff: 'Параметры'!$C$18
Name petrol_price: 'Параметры'!$C$19
Name pilot_day: 'Параметры'!$C$21
Name helpers_count: 'Параметры'!$C$22
Name helper_day: 'Параметры'!$C$23
Name vehicle_km: 'Параметры'!$C$24
Name diesel_l_100km: 'Параметры'!$C$25
Name diesel_price: 'Параметры'!$C$26
Name vehicle_wear_km: 'Параметры'!$C$27
Name per_diem_day: 'Параметры'!$C$28
Name other_day: 'Параметры'!$C$29
Name drone_wear_usd_h: 'Параметры'!$C$31
Name fert_wear_premium: 'Параметры'!$C$32
Name spreader_price_usd: 'Параметры'!$C$33
Name spreader_life_seasons: 'Параметры'!$C$34
Name drone_price_usd: 'Параметры'!$C$35
Name drone_life_years: 'Параметры'!$C$36
Name drone_dep_winter_share: 'Параметры'!$C$37
Name overhead_pct: 'Параметры'!$C$39
Name target_margin_pct: 'Параметры'!$C$40
Name usd_rate: 'Параметры'!$C$41
Name liquid_tariff_external: 'Параметры'!$C$43
Name liquid_tariff_internal: 'Параметры'!$C$44
Name nitrate_price_t: 'Параметры'!$C$45
Name urea_price_t: 'Параметры'!$C$46
Name wheat_price_t: 'Параметры'!$C$47
Name wheat_yield_t_ha: 'Параметры'!$C$48
Name ground_spread_cost_ha: 'Параметры'!$C$49
Name liq_ha_per_flight: 'Параметры'!$C$51
Name liq_flight_min: 'Параметры'!$C$52
Name liq_refill_min: 'Параметры'!$C$53
Name liq_cycle_equiv_min: 'Параметры'!$C$54
Name drones_in_winter: 'Параметры'!$C$56
Name spreaders_owned: 'Параметры'!$C$57
Name season_one_time_other: 'Параметры'!$C$58

Sheet Параметры
A1: Код | B1: Параметр | C1: Значение | D1: Единица | E1: Тип | F1: Источник / комментарий
B2: ТЕХНИКА И ФИЗИКА ПОЛЁТА
A3: payload_kg | B3: Полезная нагрузка за вылет | C3: 45 | D3: кг | E3: ОЦЕНКА | F3: Владелец: 40-50 кг. Паспорт DJI: бак 70 л, до 50 кг.
A4: swath_eff_m | B4: Ширина захвата (шаг проходов) | C4: 7 | D4: м | E4: ФАКТ | F4: Нормативная таблица владельца (30.10.2026): ширина разбрасывания 7 м, высота 3 м.
A5: speed_ms | B5: Предельная скорость над полем | C5: 6 | D5: м/с | E5: ОЦЕНКА | F5: Фактическая скорость задаётся подачей гранул (см. flow_kg_min); норматив опрыскивания 22-36 км/ч. Для гранул 6 м/с = 21,6 км/ч -- потолок.
A6: overhead_min | B6: Накладное время вылета (взлёт, подлёт, посадка) | C6: 1.5 | D6: мин | E6: ДОГАДКА | F6: Станция у кромки поля, подлёт до 300 м. Проверить пилотом.
A7: reload_min | B7: Загрузка бака и смена батареи | C7: 1.5 | D7: мин | E7: ДОГАДКА | F7: Два помощника, мешок 50 кг, засыпка по весовому датчику. Главный рычаг.
A8: eff_hours_per_day | B8: Эффективное лётное время за день | C8: 3 | D8: ч | E8: ОЦЕНКА | F8: Сентябрь: ~7 000 га / 15 бортов / ~25 дней при 1,0-1,25 га за вылет -> ~3 ч чистого налёта в день.
A9: days_per_season | B9: Рабочих дней за зимний сезон на борт | C9: 30 | D9: дн | E9: ДОГАДКА | F9: Окно подкормки ~1.02-20.03 (48 дней) минус выходные и погода.
A10: flow_kg_min | B10: Рабочая подача гранул разбрасывателем | C10: 30 | D10: кг/мин | E10: ОЦЕНКА | F10: Из нормативной таблицы: карбамид/аммофос 200 кг/га при 11 км/ч и 7 м = 26 кг/мин; селитра 400 кг/га при 8 км/ч = 37 кг/мин. Тест DJI 149 кг/га при 7 м/с = 44. Ритейлеры пишут до 90 -- для крупных гранул.
A11: cycle_equiv_min | B11: Минут полёта на один полный цикл батареи | C11: 9 | D11: мин | E11: ОЦЕНКА | F11: DJI: висение 6 мин при 101 кг (полный бак), 18 мин при 50 кг (пустой); вес падает по ходу вылета.
A12: max_flight_min | B12: Предельная длительность вылета при лёгкой загрузке | C12: 10 | D12: мин | E12: ОЦЕНКА | F12: Висение 18 мин без груза; с запасом на возврат ~10-12 мин. Режет вылет при нормах ниже ~25 кг/га (семена).
B13: БАТАРЕИ И ЭНЕРГИЯ
A14: battery_price_usd | B14: Цена батареи T40 (DB1560, 30 000 мА·ч) | C14: 1800 | D14: USD | E14: ДОГАДКА | F14: Розница США 2 499 USD; поставки из Китая дешевле. Уточнить у поставщика.
A15: battery_cycles | B15: Ресурс батареи | C15: 1200 | D15: циклов | E15: ОЦЕНКА | F15: Гарантия DJI по данным ритейлеров: 1 000-1 500 циклов.
A16: battery_kwh | B16: Ёмкость батареи | C16: 1.567 | D16: кВт·ч | E16: ФАКТ | F16: 30 А·ч x 52,22 В.
A17: gen_l_per_kwh | B17: Расход бензина генератором D12000iE | C17: 0.5 | D17: л/кВт·ч | E17: ФАКТ | F17: Паспорт DJI: 500 мл/кВт·ч.
A18: charge_eff | B18: КПД зарядки (доля энергии, дошедшей в батарею) | C18: 0.85 | D18: доля | E18: ДОГАДКА
A19: petrol_price | B19: Цена бензина АИ-92 | C19: 13000 | D19: сум/л | E19: ФАКТ | F19: Ташкент, 22.09.2026: 12 600 (местный) / 13 900 (импортный).
B20: ЛЮДИ И ТРАНСПОРТ (НА РАБОЧИЙ ДЕНЬ)
A21: pilot_day | B21: Оплата пилота за рабочий день | C21: 400000 | D21: сум | E21: ДОГАДКА | F21: Paylab: операторы сельхозтехники 3,6-7,4 млн/мес; пилот дрона выше. Уточнить по своим ведомостям.
A22: helpers_count | B22: Помощников на загрузке | C22: 2 | D22: чел | E22: ДОГАДКА | F22: Один человек 60 мешков по 45 кг за день не поднимет.
A23: helper_day | B23: Оплата помощника за день | C23: 180000 | D23: сум | E23: ДОГАДКА
A24: vehicle_km | B24: Пробег машины сопровождения за день | C24: 100 | D24: км | E24: ДОГАДКА
A25: diesel_l_100km | B25: Расход дизеля машины сопровождения | C25: 12 | D25: л/100 км | E25: ДОГАДКА
A26: diesel_price | B26: Цена дизельного топлива | C26: 15000 | D26: сум/л | E26: ОЦЕНКА | F26: АЗС Ташкента 14 700-15 900; биржа апрель 2026: 15,86 млн сум/т.
A27: vehicle_wear_km | B27: Износ машины сопровождения | C27: 1500 | D27: сум/км | E27: ДОГАДКА
A28: per_diem_day | B28: Питание и проживание экипажа | C28: 100000 | D28: сум/день | E28: ДОГАДКА
A29: other_day | B29: Прочее за день (износ генератора, связь, промывка) | C29: 50000 | D29: сум/день | E29: ДОГАДКА
B30: ИЗНОС И АМОРТИЗАЦИЯ ТЕХНИКИ
A31: drone_wear_usd_h | B31: Ремонтный резерв дрона за лётный час | C31: 5 | D31: USD/ч | E31: ДОГАДКА | F31: Винты, моторы, мелкий ремонт: ~2 500 USD на 500 лётных часов.
A32: fert_wear_premium | B32: Надбавка к износу за удобрения (коррозия, пыль) | C32: 0.5 | D32: доля | E32: ДОГАДКА | F32: Селитра -- самое коррозионно-активное удобрение (РГАУ-МСХА, 2026).
A33: spreader_price_usd | B33: Цена разбрасывателя T40 Spreading System 3.0 | C33: 1300 | D33: USD | E33: ФАКТ | F33: Розница 1 199-1 499 USD (2025).
A34: spreader_life_seasons | B34: Срок службы разбрасывателя | C34: 2 | D34: сезонов | E34: ДОГАДКА
A35: drone_price_usd | B35: Цена дрона T40 (без разбрасывателя) | C35: 20000 | D35: USD | E35: ОЦЕНКА | F35: Б/у 2025 с 3 АКБ: 19 000 USD; новый без АКБ 13 500-16 000 USD.
A36: drone_life_years | B36: Срок амортизации дрона | C36: 5 | D36: лет | E36: ДОГАДКА
A37: drone_dep_winter_share | B37: Доля годовой амортизации дрона, относимая на зиму | C37: 0 | D37: доля | E37: РЕШЕНИЕ | F37: 0 = парк уже окупается летом (маржинальный взгляд). 0,2-0,3 = полная себестоимость.
B38: НАКЛАДНЫЕ, МАРЖА, КУРС
A39: overhead_pct | B39: Накладные расходы (диспетчер, учёт, страховка) | C39: 0.1 | D39: доля выручки | E39: ДОГАДКА
A40: target_margin_pct | B40: Целевая маржа | C40: 0.25 | D40: доля выручки | E40: РЕШЕНИЕ | F40: Задаёт владелец.
A41: usd_rate | B41: Курс USD/UZS | C41: 12000 | D41: сум | E41: ФАКТ | F41: ЦБ РУз 29.10.2026: 11 965-12 004.
B42: РЫНОК И СТОРОНА ФЕРМЕРА
A43: liquid_tariff_external | B43: Текущий тариф опрыскивания, внешние заказчики | C43: 200000 | D43: сум/га | E43: ФАКТ | F43: Владелец.
A44: liquid_tariff_internal | B44: Ставка внутреннего контура (земли Агрокластера) | C44: 80000 | D44: сум/га | E44: ФАКТ | F44: Книги сентября 2025: 75 040 / 76 458 / 85 633 / 86 000.
A45: nitrate_price_t | B45: Аммиачная селитра (34,4% N) | C45: 3770000 | D45: сум/т | E45: ФАКТ | F45: UZEX, август 2026: 3 766,5 тыс. сум/т.
A46: urea_price_t | B46: Карбамид (46% N) | C46: 3000000 | D46: сум/т | E46: ДОГАДКА | F46: Свежей биржевой цены 2026 не найдено; мировая ~700 USD/т (апр. 2026).
A47: wheat_price_t | B47: Цена пшеницы для фермера | C47: 3500000 | D47: сум/т | E47: ДОГАДКА | F47: С 2022 закупка по рыночным ценам; цифру 2026 не нашли.
A48: wheat_yield_t_ha | B48: Урожайность пшеницы фермера | C48: 6.5 | D48: т/га | E48: ДОГАДКА
A49: ground_spread_cost_ha | B49: Альтернатива фермера: трактор/вручную | C49: 100000 | D49: сум/га | E49: ДОГАДКА | F49: Ориентир РФ (Татарстан): ~300 руб/га ~ 45 тыс. сум. Местные МТП -- уточнить.
B50: КАЛИБРОВКА ПО ЖИДКОЙ ОБРАБОТКЕ
A51: liq_ha_per_flight | B51: Гектаров за вылет при опрыскивании | C51: 1.2 | D51: га | E51: ФАКТ | F51: Данные вылетов: 1,0-1,25 га за вылет, 27-41 л/га.
A52: liq_flight_min | B52: Длительность вылета при опрыскивании | C52: 6.5 | D52: мин | E52: ОЦЕНКА
A53: liq_refill_min | B53: Заправка раствора и смена батареи | C53: 2.5 | D53: мин | E53: ДОГАДКА
A54: liq_cycle_equiv_min | B54: Минут полёта на цикл батареи (опрыскивание) | C54: 10 | D54: мин | E54: ОЦЕНКА | F54: DJI: 7 мин висения при 90 кг.
B55: СЕЗОН
A56: drones_in_winter | B56: Бортов в зимней работе | C56: 5 | D56: шт | E56: РЕШЕНИЕ | F56: Из 15 в парке.
A57: spreaders_owned | B57: Разбрасывателей уже есть | C57: 1 | D57: шт | E57: ФАКТ | F57: Один тестовый бак.
A58: season_one_time_other | B58: Разовые расходы сезона (обучение, демо, оснастка загрузки) | C58: 20000000 | D58: сум | E58: ДОГАДКА
B60: Жёлтые ячейки -- входы. Всё остальное в книге считается из них. Тип: ФАКТ -- с источником; ОЦЕНКА -- вывод из фактов; ДОГАДКА -- не проверено; РЕШЕНИЕ -- задаёт владелец.

Sheet Расчёт
A1: Сценарий | C1: База 100 кг/га | D1: База 150 кг/га (карбамид) | E1: База 200 кг/га | F1: База 250 кг/га (селитра) | G1: Пессимистичный 250 | H1: Оптимистичный 250 | I1: Маржинальный 250 (пилот на окладе) | J1: Пессимистичный 150 | K1: Оптимистичный 150 | L1: Норматив: селитра 400 кг/га | M1: Аэросев саксаула 4 кг/га (бак ~12 кг по объёму) | N1: Сев люцерны 15 кг/га | O1: Подсев озимых 60 кг/га | P1: Чувств. 250: эффективные часы x0.80 | Q1: Чувств. 250: эффективные часы x1.20 | R1: Чувств. 250: время загрузки x0.80 | S1: Чувств. 250: время загрузки x1.20 | T1: Чувств. 250: накладное время вылета x0.80 | U1: Чувств. 250: накладное время вылета x1.20 | V1: Чувств. 250: полезная нагрузка x0.90 | W1: Чувств. 250: полезная нагрузка x1.10 | X1: Чувств. 250: подача гранул x0.80 | Y1: Чувств. 250: подача гранул x1.20 | Z1: Чувств. 250: цена батареи x0.80 | AA1: Чувств. 250: цена батареи x1.20 | AB1: Чувств. 250: оплата пилота x0.80 | AC1: Чувств. 250: оплата пилота x1.20 | AD1: Чувств. 250: цена бензина x0.80 | AE1: Чувств. 250: цена бензина x1.20 | AF1: Чувств. 250: ресурс батареи x0.80 | AG1: Чувств. 250: ресурс батареи x1.20 | AH1: Чувств. 250: рабочих дней в сезоне x0.80 | AI1: Чувств. 250: рабочих дней в сезоне x1.20
A2: Норма внесения | B2: кг/га | C2: 100 | D2: 150 | E2: 200 | F2: 250 | G2: 250 | H2: 250 | I2: 250 | J2: 150 | K2: 150 | L2: 400 | M2: 4 | N2: 15 | O2: 60 | P2: 250 | Q2: 250 | R2: 250 | S2: 250 | T2: 250 | U2: 250 | V2: 250 | W2: 250 | X2: 250 | Y2: 250 | Z2: 250 | AA2: 250 | AB2: 250 | AC2: 250 | AD2: 250 | AE2: 250 | AF2: 250 | AG2: 250 | AH2: 250 | AI2: 250
A3: Множитель: эффективные часы | B3: x | C3: 1 | D3: 1 | E3: 1 | F3: 1 | G3: 0.66666667 | H3: 1.5 | I3: 1 | J3: 0.66666667 | K3: 1.5 | L3: 1 | M3: 1 | N3: 1 | O3: 1 | P3: 0.8 | Q3: 1.2 | R3: 1 | S3: 1 | T3: 1 | U3: 1 | V3: 1 | W3: 1 | X3: 1 | Y3: 1 | Z3: 1 | AA3: 1 | AB3: 1 | AC3: 1 | AD3: 1 | AE3: 1 | AF3: 1 | AG3: 1 | AH3: 1 | AI3: 1
A4: Множитель: время загрузки | B4: x | C4: 1 | D4: 1 | E4: 1 | F4: 1 | G4: 2 | H4: 0.66666667 | I4: 1 | J4: 2 | K4: 0.66666667 | L4: 1 | M4: 1 | N4: 1 | O4: 1 | P4: 1 | Q4: 1 | R4: 0.8 | S4: 1.2 | T4: 1 | U4: 1 | V4: 1 | W4: 1 | X4: 1 | Y4: 1 | Z4: 1 | AA4: 1 | AB4: 1 | AC4: 1 | AD4: 1 | AE4: 1 | AF4: 1 | AG4: 1 | AH4: 1 | AI4: 1
A5: Множитель: накладное время вылета | B5: x | C5: 1 | D5: 1 | E5: 1 | F5: 1 | G5: 1.3333333 | H5: 0.8 | I5: 1 | J5: 1.3333333 | K5: 0.8 | L5: 1 | M5: 1 | N5: 1 | O5: 1 | P5: 1 | Q5: 1 | R5: 1 | S5: 1 | T5: 0.8 | U5: 1.2 | V5: 1 | W5: 1 | X5: 1 | Y5: 1 | Z5: 1 | AA5: 1 | AB5: 1 | AC5: 1 | AD5: 1 | AE5: 1 | AF5: 1 | AG5: 1 | AH5: 1 | AI5: 1
A6: Множитель: полезная нагрузка | B6: x | C6: 1 | D6: 1 | E6: 1 | F6: 1 | G6: 0.88888889 | H6: 1.1111111 | I6: 1 | J6: 0.88888889 | K6: 1.1111111 | L6: 1 | M6: 0.26666667 | N6: 1 | O6: 1 | P6: 1 | Q6: 1 | R6: 1 | S6: 1 | T6: 1 | U6: 1 | V6: 0.9 | W6: 1.1 | X6: 1 | Y6: 1 | Z6: 1 | AA6: 1 | AB6: 1 | AC6: 1 | AD6: 1 | AE6: 1 | AF6: 1 | AG6: 1 | AH6: 1 | AI6: 1
A7: Множитель: цена батареи | B7: x | C7: 1 | D7: 1 | E7: 1 | F7: 1 | G7: 1 | H7: 1 | I7: 1 | J7: 1 | K7: 1 | L7: 1 | M7: 1 | N7: 1 | O7: 1 | P7: 1 | Q7: 1 | R7: 1 | S7: 1 | T7: 1 | U7: 1 | V7: 1 | W7: 1 | X7: 1 | Y7: 1 | Z7: 0.8 | AA7: 1.2 | AB7: 1 | AC7: 1 | AD7: 1 | AE7: 1 | AF7: 1 | AG7: 1 | AH7: 1 | AI7: 1
A8: Множитель: оплата пилота | B8: x | C8: 1 | D8: 1 | E8: 1 | F8: 1 | G8: 1 | H8: 1 | I8: 0.4 | J8: 1 | K8: 1 | L8: 1 | M8: 1 | N8: 1 | O8: 1 | P8: 1 | Q8: 1 | R8: 1 | S8: 1 | T8: 1 | U8: 1 | V8: 1 | W8: 1 | X8: 1 | Y8: 1 | Z8: 1 | AA8: 1 | AB8: 0.8 | AC8: 1.2 | AD8: 1 | AE8: 1 | AF8: 1 | AG8: 1 | AH8: 1 | AI8: 1
A9: Множитель: цена бензина | B9: x | C9: 1 | D9: 1 | E9: 1 | F9: 1 | G9: 1 | H9: 1 | I9: 1 | J9: 1 | K9: 1 | L9: 1 | M9: 1 | N9: 1 | O9: 1 | P9: 1 | Q9: 1 | R9: 1 | S9: 1 | T9: 1 | U9: 1 | V9: 1 | W9: 1 | X9: 1 | Y9: 1 | Z9: 1 | AA9: 1 | AB9: 1 | AC9: 1 | AD9: 0.8 | AE9: 1.2 | AF9: 1 | AG9: 1 | AH9: 1 | AI9: 1
A10: Множитель: ресурс батареи | B10: x | C10: 1 | D10: 1 | E10: 1 | F10: 1 | G10: 1 | H10: 1 | I10: 1 | J10: 1 | K10: 1 | L10: 1 | M10: 1 | N10: 1 | O10: 1 | P10: 1 | Q10: 1 | R10: 1 | S10: 1 | T10: 1 | U10: 1 | V10: 1 | W10: 1 | X10: 1 | Y10: 1 | Z10: 1 | AA10: 1 | AB10: 1 | AC10: 1 | AD10: 1 | AE10: 1 | AF10: 0.8 | AG10: 1.2 | AH10: 1 | AI10: 1
A11: Множитель: рабочих дней в сезоне | B11: x | C11: 1 | D11: 1 | E11: 1 | F11: 1 | G11: 1 | H11: 1 | I11: 1 | J11: 1 | K11: 1 | L11: 1 | M11: 1 | N11: 1 | O11: 1 | P11: 1 | Q11: 1 | R11: 1 | S11: 1 | T11: 1 | U11: 1 | V11: 1 | W11: 1 | X11: 1 | Y11: 1 | Z11: 1 | AA11: 1 | AB11: 1 | AC11: 1 | AD11: 1 | AE11: 1 | AF11: 1 | AG11: 1 | AH11: 0.8 | AI11: 1.2
A12: Множитель: ширина захвата | B12: x | C12: 1 | D12: 1 | E12: 1 | F12: 1 | G12: 1 | H12: 1 | I12: 1 | J12: 1 | K12: 1 | L12: 1 | M12: 1 | N12: 1 | O12: 1 | P12: 1 | Q12: 1 | R12: 1 | S12: 1 | T12: 1 | U12: 1 | V12: 1 | W12: 1 | X12: 1 | Y12: 1 | Z12: 1 | AA12: 1 | AB12: 1 | AC12: 1 | AD12: 1 | AE12: 1 | AF12: 1 | AG12: 1 | AH12: 1 | AI12: 1
A13: Множитель: скорость | B13: x | C13: 1 | D13: 1 | E13: 1 | F13: 1 | G13: 1 | H13: 1 | I13: 1 | J13: 1 | K13: 1 | L13: 1 | M13: 1 | N13: 1 | O13: 1 | P13: 1 | Q13: 1 | R13: 1 | S13: 1 | T13: 1 | U13: 1 | V13: 1 | W13: 1 | X13: 1 | Y13: 1 | Z13: 1 | AA13: 1 | AB13: 1 | AC13: 1 | AD13: 1 | AE13: 1 | AF13: 1 | AG13: 1 | AH13: 1 | AI13: 1
A14: Множитель: подача гранул | B14: x | C14: 1 | D14: 1 | E14: 1 | F14: 1 | G14: 1 | H14: 1 | I14: 1 | J14: 1 | K14: 1 | L14: 1 | M14: 1 | N14: 1 | O14: 1 | P14: 1 | Q14: 1 | R14: 1 | S14: 1 | T14: 1 | U14: 1 | V14: 1 | W14: 1 | X14: 0.8 | Y14: 1.2 | Z14: 1 | AA14: 1 | AB14: 1 | AC14: 1 | AD14: 1 | AE14: 1 | AF14: 1 | AG14: 1 | AH14: 1 | AI14: 1
A15: ДЕЙСТВУЮЩИЕ ВХОДЫ СЦЕНАРИЯ
A16: Полезная нагрузка | B16: кг | C16: =payload_kg*C6 | D16: =payload_kg*D6 | E16: =payload_kg*E6 | F16: =payload_kg*F6 | G16: =payload_kg*G6 | H16: =payload_kg*H6 | I16: =payload_kg*I6 | J16: =payload_kg*J6 | ... AI16: =payload_kg*AI6
A17: Эффективное лётное время | B17: ч/день | C17: =eff_hours_per_day*C3 | D17: =eff_hours_per_day*D3 | E17: =eff_hours_per_day*E3 | F17: =eff_hours_per_day*F3 | G17: =eff_hours_per_day*G3 | H17: =eff_hours_per_day*H3 | I17: =eff_hours_per_day*I3 | J17: =eff_hours_per_day*J3 | ... AI17: =eff_hours_per_day*AI3
A18: Загрузка и смена батареи | B18: мин | C18: =reload_min*C4 | D18: =reload_min*D4 | E18: =reload_min*E4 | F18: =reload_min*F4 | G18: =reload_min*G4 | H18: =reload_min*H4 | I18: =reload_min*I4 | J18: =reload_min*J4 | ... AI18: =reload_min*AI4
A19: Накладное время вылета | B19: мин | C19: =overhead_min*C5 | D19: =overhead_min*D5 | E19: =overhead_min*E5 | F19: =overhead_min*F5 | G19: =overhead_min*G5 | H19: =overhead_min*H5 | I19: =overhead_min*I5 | J19: =overhead_min*J5 | ... AI19: =overhead_min*AI5
A20: Цена батареи | B20: USD | C20: =battery_price_usd*C7 | D20: =battery_price_usd*D7 | E20: =battery_price_usd*E7 | F20: =battery_price_usd*F7 | G20: =battery_price_usd*G7 | H20: =battery_price_usd*H7 | I20: =battery_price_usd*I7 | J20: =battery_price_usd*J7 | ... AI20: =battery_price_usd*AI7
A21: Оплата пилота | B21: сум/день | C21: =pilot_day*C8 | D21: =pilot_day*D8 | E21: =pilot_day*E8 | F21: =pilot_day*F8 | G21: =pilot_day*G8 | H21: =pilot_day*H8 | I21: =pilot_day*I8 | J21: =pilot_day*J8 | ... AI21: =pilot_day*AI8
A22: Цена бензина | B22: сум/л | C22: =petrol_price*C9 | D22: =petrol_price*D9 | E22: =petrol_price*E9 | F22: =petrol_price*F9 | G22: =petrol_price*G9 | H22: =petrol_price*H9 | I22: =petrol_price*I9 | J22: =petrol_price*J9 | ... AI22: =petrol_price*AI9
A23: Ресурс батареи | B23: циклов | C23: =battery_cycles*C10 | D23: =battery_cycles*D10 | E23: =battery_cycles*E10 | F23: =battery_cycles*F10 | G23: =battery_cycles*G10 | H23: =battery_cycles*H10 | I23: =battery_cycles*I10 | J23: =battery_cycles*J10 | ... AI23: =battery_cycles*AI10
A24: Рабочих дней в сезоне | B24: дн | C24: =days_per_season*C11 | D24: =days_per_season*D11 | E24: =days_per_season*E11 | F24: =days_per_season*F11 | G24: =days_per_season*G11 | H24: =days_per_season*H11 | I24: =days_per_season*I11 | J24: =days_per_season*J11 | ... AI24: =days_per_season*AI11
A25: Ширина захвата | B25: м | C25: =swath_eff_m*C12 | D25: =swath_eff_m*D12 | E25: =swath_eff_m*E12 | F25: =swath_eff_m*F12 | G25: =swath_eff_m*G12 | H25: =swath_eff_m*H12 | I25: =swath_eff_m*I12 | J25: =swath_eff_m*J12 | ... AI25: =swath_eff_m*AI12
A26: Предельная скорость | B26: м/с | C26: =speed_ms*C13 | D26: =speed_ms*D13 | E26: =speed_ms*E13 | F26: =speed_ms*F13 | G26: =speed_ms*G13 | H26: =speed_ms*H13 | I26: =speed_ms*I13 | J26: =speed_ms*J13 | ... AI26: =speed_ms*AI13
A27: Рабочая подача гранул | B27: кг/мин | C27: =flow_kg_min*C14 | D27: =flow_kg_min*D14 | E27: =flow_kg_min*E14 | F27: =flow_kg_min*F14 | G27: =flow_kg_min*G14 | H27: =flow_kg_min*H14 | I27: =flow_kg_min*I14 | J27: =flow_kg_min*J14 | ... AI27: =flow_kg_min*AI14
A28: ПРОИЗВОДИТЕЛЬНОСТЬ
A29: Гектаров на одну загрузку по весу бака | B29: га | C29: =C16/C2 | D29: =D16/D2 | E29: =E16/E2 | F29: =F16/F2 | G29: =G16/G2 | H29: =H16/H2 | I29: =I16/I2 | J29: =J16/J2 | ... AI29: =AI16/AI2
A30: Скорость над полем (меньшее из предела и подачи) | B30: м/с | C30: =MIN(C26,C27*10000/(C2*C25*60)) | D30: =MIN(D26,D27*10000/(D2*D25*60)) | E30: =MIN(E26,E27*10000/(E2*E25*60)) | F30: =MIN(F26,F27*10000/(F2*F25*60)) | G30: =MIN(G26,G27*10000/(G2*G25*60)) | H30: =MIN(H26,H27*10000/(H2*H25*60)) | I30: =MIN(I26,I27*10000/(I2*I25*60)) | J30: =MIN(J26,J27*10000/(J2*J25*60)) | ... AI30: =MIN(AI26,AI27*10000/(AI2*AI25*60))
A31: Что ограничивает скорость | C31: =IF(C30<C26-0.000000000001,"подача гранул","предел скорости") | D31: =IF(D30<D26-0.000000000001,"подача гранул","предел скорости") | E31: =IF(E30<E26-0.000000000001,"подача гранул","предел скорости") | F31: =IF(F30<F26-0.000000000001,"подача гранул","предел скорости") | G31: =IF(G30<G26-0.000000000001,"подача гранул","предел скорости") | H31: =IF(H30<H26-0.000000000001,"подача гранул","предел скорости") | I31: =IF(I30<I26-0.000000000001,"подача гранул","предел скорости") | J31: =IF(J30<J26-0.000000000001,"подача гранул","предел скорости") | ... AI31: =IF(AI30<AI26-0.000000000001,"подача гранул","предел скорости")
A32: Время разбрасывания на гектар (без накладных) | B32: мин | C32: =10000/(C25*C30)/60 | D32: =10000/(D25*D30)/60 | E32: =10000/(E25*E30)/60 | F32: =10000/(F25*F30)/60 | G32: =10000/(G25*G30)/60 | H32: =10000/(H25*H30)/60 | I32: =10000/(I25*I30)/60 | J32: =10000/(J25*J30)/60 | ... AI32: =10000/(AI25*AI30)/60
A33: Время разбрасывания за вылет (вес бака или предел батареи) | B33: мин | C33: =MIN(C29*C32,max_flight_min-C19) | D33: =MIN(D29*D32,max_flight_min-D19) | E33: =MIN(E29*E32,max_flight_min-E19) | F33: =MIN(F29*F32,max_flight_min-F19) | G33: =MIN(G29*G32,max_flight_min-G19) | H33: =MIN(H29*H32,max_flight_min-H19) | I33: =MIN(I29*I32,max_flight_min-I19) | J33: =MIN(J29*J32,max_flight_min-J19) | ... AI33: =MIN(AI29*AI32,max_flight_min-AI19)
A34: Гектаров за вылет | B34: га | C34: =C33/C32 | D34: =D33/D32 | E34: =E33/E32 | F34: =F33/F32 | G34: =G33/G32 | H34: =H33/H32 | I34: =I33/I32 | J34: =J33/J32 | ... AI34: =AI33/AI32
A35: Вылетов на гектар | B35: шт | C35: =1/C34 | D35: =1/D34 | E35: =1/E34 | F35: =1/F34 | G35: =1/G34 | H35: =1/H34 | I35: =1/I34 | J35: =1/J34 | ... AI35: =1/AI34
A36: Внесено за вылет | B36: кг | C36: =C2*C34 | D36: =D2*D34 | E36: =E2*E34 | F36: =F2*F34 | G36: =G2*G34 | H36: =H2*H34 | I36: =I2*I34 | J36: =J2*J34 | ... AI36: =AI2*AI34
A37: Длительность вылета | B37: мин | C37: =C33+C19 | D37: =D33+D19 | E37: =E33+E19 | F37: =F33+F19 | G37: =G33+G19 | H37: =H33+H19 | I37: =I33+I19 | J37: =J33+J19 | ... AI37: =AI33+AI19
A38: Полный цикл (вылет + загрузка) | B38: мин | C38: =C37+C18 | D38: =D37+D18 | E38: =E37+E18 | F38: =F37+F18 | G38: =G37+G18 | H38: =H37+H18 | I38: =I37+I18 | J38: =J37+J18 | ... AI38: =AI37+AI18
A39: Вылетов в час | B39: шт | C39: =60/C38 | D39: =60/D38 | E39: =60/E38 | F39: =60/F38 | G39: =60/G38 | H39: =60/H38 | I39: =60/I38 | J39: =60/J38 | ... AI39: =60/AI38
A40: Внесено удобрений в час | B40: кг | C40: =C39*C36 | D40: =D39*D36 | E40: =E39*E36 | F40: =F39*F36 | G40: =G39*G36 | H40: =H39*H36 | I40: =I39*I36 | J40: =J39*J36 | ... AI40: =AI39*AI36
A41: Гектаров в час | B41: га | C41: =C39*C34 | D41: =D39*D34 | E41: =E39*E34 | F41: =F39*F34 | G41: =G39*G34 | H41: =H39*H34 | I41: =I39*I34 | J41: =J39*J34 | ... AI41: =AI39*AI34
A42: Гектаров за рабочий день | B42: га | C42: =C41*C17 | D42: =D41*D17 | E42: =E41*E17 | F42: =F41*F17 | G42: =G41*G17 | H42: =H41*H17 | I42: =I41*I17 | J42: =J41*J17 | ... AI42: =AI41*AI17
A43: Вылетов за день | B43: шт | C43: =C39*C17 | D43: =D39*D17 | E43: =E39*E17 | F43: =F39*F17 | G43: =G39*G17 | H43: =H39*H17 | I43: =I39*I17 | J43: =J39*J17 | ... AI43: =AI39*AI17
A44: Тонн за день | B44: т | C44: =C40*C17/1000 | D44: =D40*D17/1000 | E44: =E40*E17/1000 | F44: =F40*F17/1000 | G44: =G40*G17/1000 | H44: =H40*H17/1000 | I44: =I40*I17/1000 | J44: =J40*J17/1000 | ... AI44: =AI40*AI17/1000
A45: Фактическая подача | B45: кг/мин | C45: =C36/C33 | D45: =D36/D33 | E45: =E36/E33 | F45: =F36/F33 | G45: =G36/G33 | H45: =H36/H33 | I45: =I36/I33 | J45: =J36/J33 | ... AI45: =AI36/AI33
A46: Доля цикла батареи за вылет | B46: доля | C46: =C37/cycle_equiv_min | D46: =D37/cycle_equiv_min | E46: =E37/cycle_equiv_min | F46: =F37/cycle_equiv_min | G46: =G37/cycle_equiv_min | H46: =H37/cycle_equiv_min | I46: =I37/cycle_equiv_min | J46: =J37/cycle_equiv_min | ... AI46: =AI37/cycle_equiv_min
A47: Полных зарядок батарей за день | B47: шт | C47: =C43*C46 | D47: =D43*D46 | E47: =E43*E46 | F47: =F43*F46 | G47: =G43*G46 | H47: =H43*H46 | I47: =I43*I46 | J47: =J43*J46 | ... AI47: =AI43*AI46
A48: ЗАТРАТЫ НА ОДИН ВЫЛЕТ
A49: Износ батареи | B49: сум | C49: =C20*usd_rate/C23*C46 | D49: =D20*usd_rate/D23*D46 | E49: =E20*usd_rate/E23*E46 | F49: =F20*usd_rate/F23*F46 | G49: =G20*usd_rate/G23*G46 | H49: =H20*usd_rate/H23*H46 | I49: =I20*usd_rate/I23*I46 | J49: =J20*usd_rate/J23*J46 | ... AI49: =AI20*usd_rate/AI23*AI46
A50: Бензин генератора | B50: сум | C50: =battery_kwh*C46/charge_eff*gen_l_per_kwh*C22 | D50: =battery_kwh*D46/charge_eff*gen_l_per_kwh*D22 | E50: =battery_kwh*E46/charge_eff*gen_l_per_kwh*E22 | F50: =battery_kwh*F46/charge_eff*gen_l_per_kwh*F22 | G50: =battery_kwh*G46/charge_eff*gen_l_per_kwh*G22 | H50: =battery_kwh*H46/charge_eff*gen_l_per_kwh*H22 | I50: =battery_kwh*I46/charge_eff*gen_l_per_kwh*I22 | J50: =battery_kwh*J46/charge_eff*gen_l_per_kwh*J22 | ... AI50: =battery_kwh*AI46/charge_eff*gen_l_per_kwh*AI22
A51: Износ дрона (с надбавкой за удобрения) | B51: сум | C51: =drone_wear_usd_h*usd_rate*C37/60*(1+fert_wear_premium) | D51: =drone_wear_usd_h*usd_rate*D37/60*(1+fert_wear_premium) | E51: =drone_wear_usd_h*usd_rate*E37/60*(1+fert_wear_premium) | F51: =drone_wear_usd_h*usd_rate*F37/60*(1+fert_wear_premium) | G51: =drone_wear_usd_h*usd_rate*G37/60*(1+fert_wear_premium) | H51: =drone_wear_usd_h*usd_rate*H37/60*(1+fert_wear_premium) | I51: =drone_wear_usd_h*usd_rate*I37/60*(1+fert_wear_premium) | J51: =drone_wear_usd_h*usd_rate*J37/60*(1+fert_wear_premium) | ... AI51: =drone_wear_usd_h*usd_rate*AI37/60*(1+fert_wear_premium)
A52: Итого на вылет | B52: сум | C52: =C49+C50+C51 | D52: =D49+D50+D51 | E52: =E49+E50+E51 | F52: =F49+F50+F51 | G52: =G49+G50+G51 | H52: =H49+H50+H51 | I52: =I49+I50+I51 | J52: =J49+J50+J51 | ... AI52: =AI49+AI50+AI51
A53: ЗАТРАТЫ НА РАБОЧИЙ ДЕНЬ
A54: Экипаж, транспорт, прочее | B54: сум | C54: =C21+helpers_count*helper_day+vehicle_km*(diesel_l_100km/100*diesel_price+vehicle_wear_km)+per_diem_day+other_day | D54: =D21+helpers_count*helper_day+vehicle_km*(diesel_l_100km/100*diesel_price+vehicle_wear_km)+per_diem_day+other_day | E54: =E21+helpers_count*helper_day+vehicle_km*(diesel_l_100km/100*diesel_price+vehicle_wear_km)+per_diem_day+other_day | F54: =F21+helpers_count*helper_day+vehicle_km*(diesel_l_100km/100*diesel_price+vehicle_wear_km)+per_diem_day+other_day | G54: =G21+helpers_count*helper_day+vehicle_km*(diesel_l_100km/100*diesel_price+vehicle_wear_km)+per_diem_day+other_day | H54: =H21+helpers_count*helper_day+vehicle_km*(diesel_l_100km/100*diesel_price+vehicle_wear_km)+per_diem_day+other_day | I54: =I21+helpers_count*helper_day+vehicle_km*(diesel_l_100km/100*diesel_price+vehicle_wear_km)+per_diem_day+other_day | J54: =J21+helpers_count*helper_day+vehicle_km*(diesel_l_100km/100*diesel_price+vehicle_wear_km)+per_diem_day+other_day | ... AI54: =AI21+helpers_count*helper_day+vehicle_km*(diesel_l_100km/100*diesel_price+vehicle_wear_km)+per_diem_day+other_day
A55: Батареи, бензин, износ за все вылеты | B55: сум | C55: =C52*C43 | D55: =D52*D43 | E55: =E52*E43 | F55: =F52*F43 | G55: =G52*G43 | H55: =H52*H43 | I55: =I52*I43 | J55: =J52*J43 | ... AI55: =AI52*AI43
A56: Амортизация разбрасывателя | B56: сум | C56: =spreader_price_usd*usd_rate/spreader_life_seasons/C24 | D56: =spreader_price_usd*usd_rate/spreader_life_seasons/D24 | E56: =spreader_price_usd*usd_rate/spreader_life_seasons/E24 | F56: =spreader_price_usd*usd_rate/spreader_life_seasons/F24 | G56: =spreader_price_usd*usd_rate/spreader_life_seasons/G24 | H56: =spreader_price_usd*usd_rate/spreader_life_seasons/H24 | I56: =spreader_price_usd*usd_rate/spreader_life_seasons/I24 | J56: =spreader_price_usd*usd_rate/spreader_life_seasons/J24 | ... AI56: =spreader_price_usd*usd_rate/spreader_life_seasons/AI24
A57: Амортизация дрона (зимняя доля) | B57: сум | C57: =drone_price_usd*usd_rate/drone_life_years*drone_dep_winter_share/C24 | D57: =drone_price_usd*usd_rate/drone_life_years*drone_dep_winter_share/D24 | E57: =drone_price_usd*usd_rate/drone_life_years*drone_dep_winter_share/E24 | F57: =drone_price_usd*usd_rate/drone_life_years*drone_dep_winter_share/F24 | G57: =drone_price_usd*usd_rate/drone_life_years*drone_dep_winter_share/G24 | H57: =drone_price_usd*usd_rate/drone_life_years*drone_dep_winter_share/H24 | I57: =drone_price_usd*usd_rate/drone_life_years*drone_dep_winter_share/I24 | J57: =drone_price_usd*usd_rate/drone_life_years*drone_dep_winter_share/J24 | ... AI57: =drone_price_usd*usd_rate/drone_life_years*drone_dep_winter_share/AI24
A58: Итого за день | B58: сум | C58: =C54+C55+C56+C57 | D58: =D54+D55+D56+D57 | E58: =E54+E55+E56+E57 | F58: =F54+F55+F56+F57 | G58: =G54+G55+G56+G57 | H58: =H54+H55+H56+H57 | I58: =I54+I55+I56+I57 | J58: =J54+J55+J56+J57 | ... AI58: =AI54+AI55+AI56+AI57
A59: СЕБЕСТОИМОСТЬ И ТАРИФ НА ГЕКТАР
A60: Батареи, бензин, износ | B60: сум/га | C60: =C52*C35 | D60: =D52*D35 | E60: =E52*E35 | F60: =F52*F35 | G60: =G52*G35 | H60: =H52*H35 | I60: =I52*I35 | J60: =J52*J35 | ... AI60: =AI52*AI35
A61: Экипаж, транспорт, прочее | B61: сум/га | C61: =C54/C42 | D61: =D54/D42 | E61: =E54/E42 | F61: =F54/F42 | G61: =G54/G42 | H61: =H54/H42 | I61: =I54/I42 | J61: =J54/J42 | ... AI61: =AI54/AI42
A62: Амортизация разбрасывателя | B62: сум/га | C62: =C56/C42 | D62: =D56/D42 | E62: =E56/E42 | F62: =F56/F42 | G62: =G56/G42 | H62: =H56/H42 | I62: =I56/I42 | J62: =J56/J42 | ... AI62: =AI56/AI42
A63: Амортизация дрона (зимняя доля) | B63: сум/га | C63: =C57/C42 | D63: =D57/D42 | E63: =E57/E42 | F63: =F57/F42 | G63: =G57/G42 | H63: =H57/H42 | I63: =I57/I42 | J63: =J57/J42 | ... AI63: =AI57/AI42
A64: ПРЯМАЯ СЕБЕСТОИМОСТЬ ГЕКТАРА | B64: сум/га | C64: =C60+C61+C62+C63 | D64: =D60+D61+D62+D63 | E64: =E60+E61+E62+E63 | F64: =F60+F61+F62+F63 | G64: =G60+G61+G62+G63 | H64: =H60+H61+H62+H63 | I64: =I60+I61+I62+I63 | J64: =J60+J61+J62+J63 | ... AI64: =AI60+AI61+AI62+AI63
A65: Тариф безубыточности (с накладными, без маржи) | B65: сум/га | C65: =C64/(1-overhead_pct) | D65: =D64/(1-overhead_pct) | E65: =E64/(1-overhead_pct) | F65: =F64/(1-overhead_pct) | G65: =G64/(1-overhead_pct) | H65: =H64/(1-overhead_pct) | I65: =I64/(1-overhead_pct) | J65: =J64/(1-overhead_pct) | ... AI65: =AI64/(1-overhead_pct)
A66: ЦЕЛЕВОЙ ТАРИФ (с накладными и маржой) | B66: сум/га | C66: =C64/(1-overhead_pct-target_margin_pct) | D66: =D64/(1-overhead_pct-target_margin_pct) | E66: =E64/(1-overhead_pct-target_margin_pct) | F66: =F64/(1-overhead_pct-target_margin_pct) | G66: =G64/(1-overhead_pct-target_margin_pct) | H66: =H64/(1-overhead_pct-target_margin_pct) | I66: =I64/(1-overhead_pct-target_margin_pct) | J66: =J64/(1-overhead_pct-target_margin_pct) | ... AI66: =AI64/(1-overhead_pct-target_margin_pct)
A67: Тариф безубыточности за тонну удобрения | B67: сум/т | C67: =C65/C2*1000 | D67: =D65/D2*1000 | E67: =E65/E2*1000 | F67: =F65/F2*1000 | G67: =G65/G2*1000 | H67: =H65/H2*1000 | I67: =I65/I2*1000 | J67: =J65/J2*1000 | ... AI67: =AI65/AI2*1000
A68: Целевой тариф за тонну удобрения | B68: сум/т | C68: =C66/C2*1000 | D68: =D66/D2*1000 | E68: =E66/E2*1000 | F68: =F66/F2*1000 | G68: =G66/G2*1000 | H68: =H66/H2*1000 | I68: =I66/I2*1000 | J68: =J66/J2*1000 | ... AI68: =AI66/AI2*1000
A69: Выручка за день по целевому тарифу | B69: сум | C69: =C66*C42 | D69: =D66*D42 | E69: =E66*E42 | F69: =F66*F42 | G69: =G66*G42 | H69: =H66*H42 | I69: =I66*I42 | J69: =J66*J42 | ... AI69: =AI66*AI42
A70: Маржа за день по целевому тарифу | B70: сум | C70: =C69-C58-C69*overhead_pct | D70: =D69-D58-D69*overhead_pct | E70: =E69-E58-E69*overhead_pct | F70: =F69-F58-F69*overhead_pct | G70: =G69-G58-G69*overhead_pct | H70: =H69-H58-H69*overhead_pct | I70: =I69-I58-I69*overhead_pct | J70: =J69-J58-J69*overhead_pct | ... AI70: =AI69-AI58-AI69*overhead_pct
A71: Целевой тариф к тарифу опрыскивания | B71: раз | C71: =C66/liquid_tariff_external | D71: =D66/liquid_tariff_external | E71: =E66/liquid_tariff_external | F71: =F66/liquid_tariff_external | G71: =G66/liquid_tariff_external | H71: =H66/liquid_tariff_external | I71: =I66/liquid_tariff_external | J71: =J66/liquid_tariff_external | ... AI71: =AI66/liquid_tariff_external
A72: ДВУХСТАВОЧНЫЙ ТАРИФ: ГЕКТАР + ТОННА
A73: Постоянные затраты на минуту лётного времени | B73: сум/мин | C73: =(C54+C56+C57)/(C17*60) | D73: =(D54+D56+D57)/(D17*60) | E73: =(E54+E56+E57)/(E17*60) | F73: =(F54+F56+F57)/(F17*60) | G73: =(G54+G56+G57)/(G17*60) | H73: =(H54+H56+H57)/(H17*60) | I73: =(I54+I56+I57)/(I17*60) | J73: =(J54+J56+J57)/(J17*60) | ... AI73: =(AI54+AI56+AI57)/(AI17*60)
A74: Батарея, бензин, износ на минуту полёта | B74: сум/мин | C74: =(C20*usd_rate/C23+battery_kwh/charge_eff*gen_l_per_kwh*C22)/cycle_equiv_min+drone_wear_usd_h*usd_rate/60*(1+fert_wear_premium) | D74: =(D20*usd_rate/D23+battery_kwh/charge_eff*gen_l_per_kwh*D22)/cycle_equiv_min+drone_wear_usd_h*usd_rate/60*(1+fert_wear_premium) | E74: =(E20*usd_rate/E23+battery_kwh/charge_eff*gen_l_per_kwh*E22)/cycle_equiv_min+drone_wear_usd_h*usd_rate/60*(1+fert_wear_premium) | F74: =(F20*usd_rate/F23+battery_kwh/charge_eff*gen_l_per_kwh*F22)/cycle_equiv_min+drone_wear_usd_h*usd_rate/60*(1+fert_wear_premium) | G74: =(G20*usd_rate/G23+battery_kwh/charge_eff*gen_l_per_kwh*G22)/cycle_equiv_min+drone_wear_usd_h*usd_rate/60*(1+fert_wear_premium) | H74: =(H20*usd_rate/H23+battery_kwh/charge_eff*gen_l_per_kwh*H22)/cycle_equiv_min+drone_wear_usd_h*usd_rate/60*(1+fert_wear_premium) | I74: =(I20*usd_rate/I23+battery_kwh/charge_eff*gen_l_per_kwh*I22)/cycle_equiv_min+drone_wear_usd_h*usd_rate/60*(1+fert_wear_premium) | J74: =(J20*usd_rate/J23+battery_kwh/charge_eff*gen_l_per_kwh*J22)/cycle_equiv_min+drone_wear_usd_h*usd_rate/60*(1+fert_wear_premium) | ... AI74: =(AI20*usd_rate/AI23+battery_kwh/charge_eff*gen_l_per_kwh*AI22)/cycle_equiv_min+drone_wear_usd_h*usd_rate/60*(1+fert_wear_premium)
A75: Себестоимость: постоянная часть на гектар (C0; 0, если скорость режет подача) | B75: сум/га | C75: =IF(C31="подача гранул",0,C32*(C73+C74)) | D75: =IF(D31="подача гранул",0,D32*(D73+D74)) | E75: =IF(E31="подача гранул",0,E32*(E73+E74)) | F75: =IF(F31="подача гранул",0,F32*(F73+F74)) | G75: =IF(G31="подача гранул",0,G32*(G73+G74)) | H75: =IF(H31="подача гранул",0,H32*(H73+H74)) | I75: =IF(I31="подача гранул",0,I32*(I73+I74)) | J75: =IF(J31="подача гранул",0,J32*(J73+J74)) | ... AI75: =IF(AI31="подача гранул",0,AI32*(AI73+AI74))
A76: Себестоимость: переменная часть на килограмм (c1) | B76: сум/кг | C76: =IF(C31="подача гранул",C73*(1/C27+(C19+C18)/C16)+C74*(1/C27+C19/C16),((C19+C18)*C73+C19*C74)/C16) | D76: =IF(D31="подача гранул",D73*(1/D27+(D19+D18)/D16)+D74*(1/D27+D19/D16),((D19+D18)*D73+D19*D74)/D16) | E76: =IF(E31="подача гранул",E73*(1/E27+(E19+E18)/E16)+E74*(1/E27+E19/E16),((E19+E18)*E73+E19*E74)/E16) | F76: =IF(F31="подача гранул",F73*(1/F27+(F19+F18)/F16)+F74*(1/F27+F19/F16),((F19+F18)*F73+F19*F74)/F16) | G76: =IF(G31="подача гранул",G73*(1/G27+(G19+G18)/G16)+G74*(1/G27+G19/G16),((G19+G18)*G73+G19*G74)/G16) | H76: =IF(H31="подача гранул",H73*(1/H27+(H19+H18)/H16)+H74*(1/H27+H19/H16),((H19+H18)*H73+H19*H74)/H16) | I76: =IF(I31="подача гранул",I73*(1/I27+(I19+I18)/I16)+I74*(1/I27+I19/I16),((I19+I18)*I73+I19*I74)/I16) | J76: =IF(J31="подача гранул",J73*(1/J27+(J19+J18)/J16)+J74*(1/J27+J19/J16),((J19+J18)*J73+J19*J74)/J16) | ... AI76: =IF(AI31="подача гранул",AI73*(1/AI27+(AI19+AI18)/AI16)+AI74*(1/AI27+AI19/AI16),((AI19+AI18)*AI73+AI19*AI74)/AI16)
A77: Контроль: C0 + c1 x норма - прямая себестоимость (0, пока вылет ограничен весом бака или подачей, а не батареей) | B77: сум | C77: =C75+C76*C2-C64 | D77: =D75+D76*D2-D64 | E77: =E75+E76*E2-E64 | F77: =F75+F76*F2-F64 | G77: =G75+G76*G2-G64 | H77: =H75+H76*H2-H64 | I77: =I75+I76*I2-I64 | J77: =J75+J76*J2-J64 | ... AI77: =AI75+AI76*AI2-AI64
A78: ТАРИФ: ставка за гектар | B78: сум/га | C78: =C75/(1-overhead_pct-target_margin_pct) | D78: =D75/(1-overhead_pct-target_margin_pct) | E78: =E75/(1-overhead_pct-target_margin_pct) | F78: =F75/(1-overhead_pct-target_margin_pct) | G78: =G75/(1-overhead_pct-target_margin_pct) | H78: =H75/(1-overhead_pct-target_margin_pct) | I78: =I75/(1-overhead_pct-target_margin_pct) | J78: =J75/(1-overhead_pct-target_margin_pct) | ... AI78: =AI75/(1-overhead_pct-target_margin_pct)
A79: ТАРИФ: ставка за килограмм удобрения | B79: сум/кг | C79: =C76/(1-overhead_pct-target_margin_pct) | D79: =D76/(1-overhead_pct-target_margin_pct) | E79: =E76/(1-overhead_pct-target_margin_pct) | F79: =F76/(1-overhead_pct-target_margin_pct) | G79: =G76/(1-overhead_pct-target_margin_pct) | H79: =H76/(1-overhead_pct-target_margin_pct) | I79: =I76/(1-overhead_pct-target_margin_pct) | J79: =J76/(1-overhead_pct-target_margin_pct) | ... AI79: =AI76/(1-overhead_pct-target_margin_pct)
A80: ТАРИФ: ставка за тонну удобрения | B80: сум/т | C80: =C79*1000 | D80: =D79*1000 | E80: =E79*1000 | F80: =F79*1000 | G80: =G79*1000 | H80: =H79*1000 | I80: =I79*1000 | J80: =J79*1000 | ... AI80: =AI79*1000

Sheet Чувствительность
A1: Параметр (сценарий 250 кг/га) | B1: Множитель | C1: Целевой тариф, сум/га | D1: Отклонение от базы, % | E1: Га за день | F1: Отклонение, %
A2: База 250 кг/га | B2: 1 | C2: ='Расчёт'!F66 | D2: 0 | E2: ='Расчёт'!F42 | F2: 0
A3: эффективные часы | B3: 0.8 | C3: ='Расчёт'!P66 | D3: =C3/$C$2-1 | E3: ='Расчёт'!P42 | F3: =E3/$E$2-1
A4: эффективные часы | B4: 1.2 | C4: ='Расчёт'!Q66 | D4: =C4/$C$2-1 | E4: ='Расчёт'!Q42 | F4: =E4/$E$2-1
A5: время загрузки | B5: 0.8 | C5: ='Расчёт'!R66 | D5: =C5/$C$2-1 | E5: ='Расчёт'!R42 | F5: =E5/$E$2-1
A6: время загрузки | B6: 1.2 | C6: ='Расчёт'!S66 | D6: =C6/$C$2-1 | E6: ='Расчёт'!S42 | F6: =E6/$E$2-1
A7: накладное время вылета | B7: 0.8 | C7: ='Расчёт'!T66 | D7: =C7/$C$2-1 | E7: ='Расчёт'!T42 | F7: =E7/$E$2-1
A8: накладное время вылета | B8: 1.2 | C8: ='Расчёт'!U66 | D8: =C8/$C$2-1 | E8: ='Расчёт'!U42 | F8: =E8/$E$2-1
A9: полезная нагрузка | B9: 0.9 | C9: ='Расчёт'!V66 | D9: =C9/$C$2-1 | E9: ='Расчёт'!V42 | F9: =E9/$E$2-1
A10: полезная нагрузка | B10: 1.1 | C10: ='Расчёт'!W66 | D10: =C10/$C$2-1 | E10: ='Расчёт'!W42 | F10: =E10/$E$2-1
A11: подача гранул | B11: 0.8 | C11: ='Расчёт'!X66 | D11: =C11/$C$2-1 | E11: ='Расчёт'!X42 | F11: =E11/$E$2-1
A12: подача гранул | B12: 1.2 | C12: ='Расчёт'!Y66 | D12: =C12/$C$2-1 | E12: ='Расчёт'!Y42 | F12: =E12/$E$2-1
A13: цена батареи | B13: 0.8 | C13: ='Расчёт'!Z66 | D13: =C13/$C$2-1 | E13: ='Расчёт'!Z42 | F13: =E13/$E$2-1
A14: цена батареи | B14: 1.2 | C14: ='Расчёт'!AA66 | D14: =C14/$C$2-1 | E14: ='Расчёт'!AA42 | F14: =E14/$E$2-1
A15: оплата пилота | B15: 0.8 | C15: ='Расчёт'!AB66 | D15: =C15/$C$2-1 | E15: ='Расчёт'!AB42 | F15: =E15/$E$2-1
A16: оплата пилота | B16: 1.2 | C16: ='Расчёт'!AC66 | D16: =C16/$C$2-1 | E16: ='Расчёт'!AC42 | F16: =E16/$E$2-1
A17: цена бензина | B17: 0.8 | C17: ='Расчёт'!AD66 | D17: =C17/$C$2-1 | E17: ='Расчёт'!AD42 | F17: =E17/$E$2-1
A18: цена бензина | B18: 1.2 | C18: ='Расчёт'!AE66 | D18: =C18/$C$2-1 | E18: ='Расчёт'!AE42 | F18: =E18/$E$2-1
A19: ресурс батареи | B19: 0.8 | C19: ='Расчёт'!AF66 | D19: =C19/$C$2-1 | E19: ='Расчёт'!AF42 | F19: =E19/$E$2-1
A20: ресурс батареи | B20: 1.2 | C20: ='Расчёт'!AG66 | D20: =C20/$C$2-1 | E20: ='Расчёт'!AG42 | F20: =E20/$E$2-1
A21: рабочих дней в сезоне | B21: 0.8 | C21: ='Расчёт'!AH66 | D21: =C21/$C$2-1 | E21: ='Расчёт'!AH42 | F21: =E21/$E$2-1
A22: рабочих дней в сезоне | B22: 1.2 | C22: ='Расчёт'!AI66 | D22: =C22/$C$2-1 | E22: ='Расчёт'!AI42 | F22: =E22/$E$2-1
A24: Чтение: чем больше отклонение при одинаковом множителе, тем сильнее параметр влияет на тариф. Это и есть то, что надо измерять в пилоте первым.

Sheet Сезон
A1: Показатель | B1: Единица | C1: База 150 кг/га (карбамид) | D1: База 250 кг/га (селитра)
A2: Гектаров за сезон на один борт | B2: га | C2: ='Расчёт'!D42*days_per_season | D2: ='Расчёт'!F42*days_per_season
A3: Гектаров за сезон, все борта | B3: га | C3: =C2*drones_in_winter | D3: =D2*drones_in_winter
A4: Выручка по целевому тарифу | B4: сум | C4: =C3*'Расчёт'!D66 | D4: =D3*'Расчёт'!F66
A5: Прямые затраты | B5: сум | C5: =C3*'Расчёт'!D64 | D5: =D3*'Расчёт'!F64
A6: Накладные | B6: сум | C6: =C4*overhead_pct | D6: =D4*overhead_pct
A7: Разбрасывателей докупить | B7: шт | C7: =MAX(0,drones_in_winter-spreaders_owned) | D7: =MAX(0,drones_in_winter-spreaders_owned)
A8: Разовые расходы сезона | B8: сум | C8: =C7*spreader_price_usd*usd_rate+season_one_time_other | D8: =D7*spreader_price_usd*usd_rate+season_one_time_other
A9: Маржа до разовых расходов | B9: сум | C9: =C4-C5-C6 | D9: =D4-D5-D6
A10: РЕЗУЛЬТАТ СЕЗОНА | B10: сум | C10: =C9-C8 | D10: =D9-D8
A11: Результат сезона | B11: USD | C11: =C10/usd_rate | D11: =D10/usd_rate
A13: Для сравнения: сентябрь 2026 -- около 7 000 га опрыскивания в месяц по 200 000 сум/га, то есть ~1,4 млрд сум выручки за месяц пика. Зимнее разбрасывание -- заполнение простоя, не второй сезон.

Sheet Сравнение
A1: КАЛИБРОВКА: та же модель затрат для текущего опрыскивания | B1: Единица | C1: Значение
A2: Вылетов в час | B2: шт | C2: =60/(liq_flight_min+liq_refill_min)
A3: Гектаров за день | B3: га | C3: =C2*liq_ha_per_flight*eff_hours_per_day
A4: Доля цикла батареи за вылет | B4: доля | C4: =liq_flight_min/liq_cycle_equiv_min
A5: Износ батареи за вылет | B5: сум | C5: =battery_price_usd*usd_rate/battery_cycles*C4
A6: Бензин за вылет | B6: сум | C6: =battery_kwh*C4/charge_eff*gen_l_per_kwh*petrol_price
A7: Износ дрона за вылет | B7: сум | C7: =drone_wear_usd_h*usd_rate*liq_flight_min/60
A8: Итого за вылет | B8: сум | C8: =C5+C6+C7
A9: Батареи, бензин, износ на гектар | B9: сум/га | C9: =C8/liq_ha_per_flight
A10: Экипаж, транспорт, прочее на гектар | B10: сум/га | C10: =(pilot_day+helpers_count*helper_day+vehicle_km*(diesel_l_100km/100*diesel_price+vehicle_wear_km)+per_diem_day+other_day)/C3
A11: ПРЯМАЯ СЕБЕСТОИМОСТЬ ГЕКТАРА ОПРЫСКИВАНИЯ | B11: сум/га | C11: =C9+C10
A12: Маржа с гектара при 200 000 (после накладных) | B12: сум/га | C12: =liquid_tariff_external-C11-liquid_tariff_external*overhead_pct
A13: Внутренняя ставка минус прямая себестоимость | B13: сум/га | C13: =liquid_tariff_internal-C11
A14: Чтение: прямая себестоимость опрыскивания по этой модели должна лечь рядом с внутренней ставкой 75-86 тыс. сум/га. Если нет -- входы блока «Люди и транспорт» завышены или занижены.
A16: СТОРОНА ФЕРМЕРА: селитра 200 кг/га, тариф «за тонну» базы 250
A17: Норма внесения | B17: кг/га | C17: =200
A18: Стоимость удобрения | B18: сум/га | C18: =C17/1000*nitrate_price_t
A19: Услуга дрона: ставка за тонну x норма, не ниже минимума за гектар | B19: сум/га | C19: =MAX('Расчёт'!F80*10000/(swath_eff_m*speed_ms)/60*flow_kg_min/1000,'Расчёт'!F80*C17/1000)
A20: Итого подкормка дроном | B20: сум/га | C20: =C18+C19
A21: Итого подкормка трактором/вручную | B21: сум/га | C21: =C18+ground_spread_cost_ha
A22: Надбавка за дрон против наземной альтернативы | B22: сум/га | C22: =C19-ground_spread_cost_ha
A23: Прибавка урожая, окупающая надбавку | B23: кг/га | C23: =C22/wheat_price_t*1000
A24: Та же прибавка в долях урожая | B24: доля | C24: =C23/1000/wheat_yield_t_ha
A25: Услуга к стоимости удобрения | B25: доля | C25: =C19/C18
A27: Чтение: фермеру дрон выгоден, если своевременность и равномерность дают прибавку урожая не меньше строки «Прибавка урожая, окупающая надбавку». Это главный аргумент КП, и его надо подтвердить агрономом.

Sheet Тариф для КП
A1: ТАРИФ ДЛЯ КП: ставка за тонну и минимум за гектар (из сценария «База 250», округление до 5 000 сум)
A2: Ставка за тонну внесённого удобрения | B2: сум/т | C2: =ROUND('Расчёт'!F80/5000,0)*5000
A3: Норма, ниже которой скорость ограничивает не подача, а предел скорости | B3: кг/га | C3: =10000/(swath_eff_m*speed_ms)/60*flow_kg_min
A4: Минимальная цена гектара (тариф за тонну x эта норма) | B4: сум/га | C4: =ROUND($C$2*$C$3/1000/5000,0)*5000
A6: Норма, кг/га | B6: Цена для фермера, сум/га | C6: К тарифу опрыскивания, раз
A7: 100 | B7: =MAX($C$4,$C$2*A7/1000) | C7: =B7/liquid_tariff_external
A8: 150 | B8: =MAX($C$4,$C$2*A8/1000) | C8: =B8/liquid_tariff_external
A9: 200 | B9: =MAX($C$4,$C$2*A9/1000) | C9: =B9/liquid_tariff_external
A10: 250 | B10: =MAX($C$4,$C$2*A10/1000) | C10: =B10/liquid_tariff_external
A11: 300 | B11: =MAX($C$4,$C$2*A11/1000) | C11: =B11/liquid_tariff_external
A12: 400 | B12: =MAX($C$4,$C$2*A12/1000) | C12: =B12/liquid_tariff_external
A14: Почему «за тонну»: при нормах выше ~120 кг/га скорость над полем задаёт подача гранул (норматив: 8-11 км/ч при 7 м), и время над гектаром растёт пропорционально норме, как и число вылетов. Себестоимость гектара становится почти чисто пропорциональной килограммам -- строка C0 на листе «Расчёт» равна нулю, а ставка за тонну одинакова для 150, 250 и 400 кг/га. Минимум за гектар защищает выезд на лёгких нормах.

Sheet Источники
A1: Тип | B1: Утверждение | C1: Источник
A2: ФАКТ | B2: DJI Agras T40: бак разбрасывателя 70 л / 50 кг, ширина 7 м, гранулы 0,5-5 мм, висение 6 мин при 101 кг, 7 мин при 90 кг, 18 мин при 50 кг; заявка 1,5 т/ч* при 149 кг/га, 7 м/с, 3 м | C2: Страницы DJI (dji.com/t40/specs, support) в пересказе поисковой выдачи; ритейлеры DJI (Dronefly, Ferntech, Aerosmart)
A3: ФАКТ | B3: Батарея DB1560 30 000 мА·ч, 52,22 В; розница США 2 499 USD; гарантия 1 000-1 500 циклов (ритейлеры расходятся) | C3: Dronefly, DSLRPros, Reach.dog, Maverick Drone
A4: ФАКТ | B4: Генератор D12000iE: 500 мл/кВт·ч, заряд батареи T40 9-12 мин | C4: Dronefly, Aerosmart, manualslib (пересказ)
A5: ФАКТ | B5: Разбрасыватель T40 Spreading System 3.0: 1 199-1 499 USD; подача до 90 кг/мин | C5: Uniquephoto, Rippingitoutdoors, rcdrone.top
A6: ФАКТ | B6: Дрон T40 б/у 2025 с 3 АКБ: 19 000 USD (США); новый без АКБ 13 499-15 999 USD | C6: Controller.com, Reach.dog
A7: ФАКТ | B7: АИ-92 Ташкент 22.09.2026: 12 600 / 13 900 сум/л; дизель 14 700-15 900 сум/л; биржа дизель апр. 2026 15,86 млн сум/т | C7: Avtoelon.uz, Autostrada.uz, Kun.uz
A8: ФАКТ | B8: Курс ЦБ РУз 29.10.2026: 11 965-12 004 сум/USD | C8: Kursiv.media, Repost.uz
A9: ФАКТ | B9: Аммиачная селитра UZEX, авг. 2026: 3 813,2 -> 3 766,5 тыс. сум/т | C9: Yuz.uz (биржевой обзор)
A10: ФАКТ | B10: Внутренняя ставка опрыскивания 75 040-86 000 сум/га; внешняя 200 000 сум/га; 1,0-1,25 га за вылет; 27-41 л/га; сентябрь 2026 ~7 071 га RAW по 15 бортам | C10: Репозиторий: docs/tracks/drones.md (DRONE-MONEY-001, DRONE-OCT2025-PRICE-001, UAT 30.09.2026)
A11: ФАКТ | B11: Нормативная таблица владельца (30.10.2026): опрыскивание 40 л/2 га при 36 км/ч, 6,5 м, 2 м или 20 л/2 га при 22 км/ч, 7 м, 3 м, 200 000 сум; разбрасывание 50 кг: карбамид/аммофос 0,25 га при 11 км/ч, селитра 0,125 га при 8 км/ч, ширина 7 м, высота 3 м | C11: Файл владельца, лист «Лист1»
A12: ФАКТ | B12: Март 2026 -- первая работа сезона: 1 340 га, 11 бортов; в феврале работ не было | C12: Владелец, 30.10.2026
... A19: ДОГАДКА | B19: Оплата пилота/помощников, пробег, износ, КПД зарядки, цена карбамида и пшеницы 2026, стоимость наземной альтернативы в районе | C19: Не найдено в открытых источниках -- заданы как редактируемые входы
A21: Прямое чтение сайтов из облачной сессии было закрыто сетевой политикой: цифры взяты из поисковых сводок и помечены соответственно. Перед печатью КП сверить цены у поставщика и на UZEX.
